click_spinner-stubs/METADATA.toml
click_spinner-stubs/__init__.pyi
click_spinner-stubs/_version.pyi
click_spinner-stubs/py.typed
types_click_spinner-0.1.13.20250510.dist-info/licenses/LICENSE
types_click_spinner-0.1.13.20250510.dist-info/METADATA
types_click_spinner-0.1.13.20250510.dist-info/WHEEL
types_click_spinner-0.1.13.20250510.dist-info/top_level.txt
types_click_spinner-0.1.13.20250510.dist-info/RECORD
